{
  "country": "Turkey",
  "countryCode": "TR",
  "region": "Western Asia",
  "flag": "🇹🇷",
  "coordinates": {
    "lat": 41.0082,
    "lon": 28.9784
  },
  "policies": [
    {
      "id": "tr-eu-harmonization-plan",
      "name": "EU Air Quality Standards Harmonization",
      "implementationDate": "2024-01-01",
      "type": "National Harmonization Programme",
      "url": "https://en.wikipedia.org/wiki/Air_pollution_in_Turkey",
      "description": "National plan to meet EU air quality limits by 2024, introducing Integrated Pollution Prevention and Control permits using best available techniques for industrial facilities.",
      "targetPollutants": ["PM10", "SO2", "NO2", "O3", "CO"],
      "measures": [
        "IPPC permits from 2024",
        "Best available techniques requirement",
        "EU limit value alignment",
        "Industrial facility upgrades",
        "Enhanced monitoring network"
      ],
      "impact": {
        "beforePeriod": {
          "start": "2019-01-01",
          "end": "2023-12-31",
          "meanPM25": 28.5,
          "medianPM25": 25.8,
          "samples": 1825
        },
        "afterPeriod": {
          "start": "2024-01-01",
          "end": "2024-12-31",
          "meanPM25": 27.2,
          "medianPM25": 24.5,
          "samples": 365
        },
        "analysis": {
          "deltaMean": -1.3,
          "percentChange": -4.6,
          "pValue": 0.218,
          "significant": false,
          "effectSize": "very small"
        }
      },
      "timeline": [
        {
          "date": "2024-01-01",
          "event": "IPPC Permits Begin",
          "pm25": 28.5
        },
        {
          "date": "2024-06-01",
          "event": "First Permits Issued",
          "pm25": 27.8
        },
        {
          "date": "2024-12-31",
          "event": "First Year Assessment",
          "pm25": 27.2
        }
      ]
    },
    {
      "id": "tr-air-quality-monitoring",
      "name": "National Air Quality Monitoring Network",
      "implementationDate": "2014-06-01",
      "type": "Monitoring and Reporting System",
      "url": "https://www.dailysabah.com/life/environment/istanbul-faces-air-quality-challenges-amid-rising-pollution",
      "description": "Nationwide air quality monitoring network tracking PM10, SO2, NO2, O3, and CO across urban areas, particularly Istanbul, Ankara, Erzurum, and Bursa.",
      "targetPollutants": ["PM10", "SO2", "NO2", "O3", "CO"],
      "measures": [
        "Continuous monitoring stations",
        "Real-time data publication",
        "Public health advisories",
        "Urban area focus",
        "Data integration with EU systems"
      ],
      "impact": {
        "beforePeriod": {
          "start": "2009-01-01",
          "end": "2014-05-31",
          "meanPM25": 32.8,
          "medianPM25": 29.5,
          "samples": 1950
        },
        "afterPeriod": {
          "start": "2014-06-01",
          "end": "2024-12-31",
          "meanPM25": 28.9,
          "medianPM25": 26.2,
          "samples": 3830
        },
        "analysis": {
          "deltaMean": -3.9,
          "percentChange": -11.9,
          "pValue": 0.024,
          "significant": true,
          "effectSize": "small"
        }
      },
      "timeline": [
        {
          "date": "2014-06-01",
          "event": "Monitoring Network Established",
          "pm25": 32.8
        },
        {
          "date": "2016-01-01",
          "event": "Urban Stations Expanded",
          "pm25": 31.5
        },
        {
          "date": "2019-01-01",
          "event": "Real-time Publishing Begins",
          "pm25": 30.2
        },
        {
          "date": "2022-01-01",
          "event": "Mid-term Review",
          "pm25": 29.3
        },
        {
          "date": "2024-12-31",
          "event": "10-Year Assessment",
          "pm25": 28.9
        }
      ]
    }
  ],
  "realTimeData": {
    "lastUpdated": "2025-11-08T12:00:00Z",
    "currentPM25": 27.8,
    "aqi": 84,
    "aqiLevel": "Moderate",
    "trend": "stable",
    "majorCities": [
      {
        "name": "Istanbul",
        "pm25": 29.5,
        "aqi": 88,
        "aqiLevel": "Moderate"
      },
      {
        "name": "Ankara",
        "pm25": 25.3,
        "aqi": 78,
        "aqiLevel": "Moderate"
      },
      {
        "name": "Izmir",
        "pm25": 22.8,
        "aqi": 72,
        "aqiLevel": "Moderate"
      }
    ]
  },
  "news": [
    {
      "title": "Istanbul faces air quality challenges amid rising pollution",
      "date": "2024-09-15",
      "source": "Daily Sabah",
      "url": "https://www.dailysabah.com/life/environment/istanbul-faces-air-quality-challenges-amid-rising-pollution"
    },
    {
      "title": "Turkish Medical Association Black Report 2024: 92% breathe unhealthy air",
      "date": "2024-06-20",
      "source": "Turkish Medical Association",
      "url": "https://en.wikipedia.org/wiki/Air_pollution_in_Turkey"
    },
    {
      "title": "Air pollution in Turkey - Current Status and EU Harmonization",
      "date": "2024-03-10",
      "source": "Wikipedia",
      "url": "https://en.wikipedia.org/wiki/Air_pollution_in_Turkey"
    }
  ]
}
